README.md
setup.cfg
setup.py
ecr2ecr/__init__.py
ecr2ecr/core.py
ecr2ecr.egg-info/PKG-INFO
ecr2ecr.egg-info/SOURCES.txt
ecr2ecr.egg-info/dependency_links.txt
ecr2ecr.egg-info/entry_points.txt
ecr2ecr.egg-info/requires.txt
ecr2ecr.egg-info/top_level.txt
tests/__init__.py
tests/test_ecr2ecr.py