Metadata-Version: 1.0
Name: ecr2ecr
Version: 1.26
Summary: docker image registry sync tools. Currently supports aws ecr.
Home-page: https://pypi.org/project/ecr2ecr
Author: Jasper Culong
Author-email: jculongit10@yahoo.com
License: LICENSE
Platform: UNKNOWN
